llama_index/packs/longrag/__init__.py
llama_index/packs/longrag/base.py
llama_index_packs_longrag-0.5.0.dist-info/METADATA
llama_index_packs_longrag-0.5.0.dist-info/WHEEL
llama_index_packs_longrag-0.5.0.dist-info/licenses/LICENSE
llama_index_packs_longrag-0.5.0.dist-info/RECORD
